mcpdf/__init__.py
mcpdf/cli/__init__.py
mcpdf/cli/base.py
mcpdf/cli/evolve.py
mcpdf/cli/log.py
mcpdf/cli/report.py
mcpdf/fit/__init__.py
mcpdf/fit/evolve.py
mcpdf/fit/install.py
mcpdf/fit/report.py
mcpdf/fit/runcard-base/runcard.yaml
mcpdf/fit/runcard-full/data.md
mcpdf/fit/runcard-full/exponents.md
mcpdf/fit/runcard-full/lumi.md
mcpdf/fit/runcard-full/pdf.md
mcpdf/fit/runcard-full/report.md
mcpdf/fit/runcard-full/runcard-full.yaml
mcpdf/fit/runcard-short/runcard.yaml
mcpdf/generate.py
mcpdf/nnpdf/__init__.py
mcpdf/nnpdf/data.py
mcpdf/nnpdf/defaults.py
mcpdf/nnpdf/theory.py
mcpdf-0.1.0.dist-info/METADATA
mcpdf-0.1.0.dist-info/WHEEL
mcpdf-0.1.0.dist-info/entry_points.txt
mcpdf-0.1.0.dist-info/RECORD
