Metadata-Version: 2.1
Name: mcpdf
Version: 0.1.0
Summary: 
Author: Alessandro Candido
Author-email: candido.ale@gmail.com
Requires-Python: >=3.10,<3.11
Classifier: Programming Language :: Python :: 3
Classifier: Programming Language :: Python :: 3.10
Requires-Dist: PyYAML (>=6.0,<7.0)
Requires-Dist: a3b2bbc3ced97675ac3a71df45f55ba (>=6.4.0,<7.0.0)
Requires-Dist: click (>=8.1.3,<9.0.0)
Requires-Dist: eko[box] (>=0.10.0,<0.11.0)
Requires-Dist: numpy (>=1.22.3,<2.0.0)
Requires-Dist: rich (>=12.5.1,<13.0.0)
